setup.py
mathhero/__init__.py
mathhero.egg-info/PKG-INFO
mathhero.egg-info/SOURCES.txt
mathhero.egg-info/dependency_links.txt
mathhero.egg-info/not-zip-safe
mathhero.egg-info/requires.txt
mathhero.egg-info/top_level.txt