Metadata-Version: 1.0
Name: mathhero
Version: 0.1
Summary: This package integrates mathematical tools for complex data analysis
Home-page: http://gitlab.com/porterjs/mathhero
Author: JEBBS
Author-email: jasonsporter88@gmail.com
License: JSP
Keywords: mathhero math hero solver data engineering
Platform: UNKNOWN
